fresco/__init__.py
fresco/run_clc.py
fresco/run_ie.py
fresco/abstention/__init__.py
fresco/abstention/abstention.py
fresco/data_loaders/__init__.py
fresco/data_loaders/data_utils.py
fresco/models/__init__.py
fresco/models/clc.py
fresco/models/cnn.py
fresco/models/mtcnn.py
fresco/models/mthisan.py
fresco/predict/__init__.py
fresco/predict/predictions.py
fresco/training/__init__.py
fresco/training/training.py
fresco/validate/__init__.py
fresco/validate/exceptions.py
fresco/validate/validate_params.py
nci_fresco-0.2.6.dist-info/LICENSE
nci_fresco-0.2.6.dist-info/METADATA
nci_fresco-0.2.6.dist-info/WHEEL
nci_fresco-0.2.6.dist-info/top_level.txt
nci_fresco-0.2.6.dist-info/RECORD
